manven/__init__.py
manven/__main__.py
manven/cli.py
manven/commands.py
manven/settings.py
manven/toolbox.py
manven-0.5.1.data/scripts/manven
manven-0.5.1.data/scripts/manven.fish
manven-0.5.1.dist-info/METADATA
manven-0.5.1.dist-info/WHEEL
manven-0.5.1.dist-info/top_level.txt
manven-0.5.1.dist-info/RECORD
