Metadata-Version: 2.1
Name: manven
Version: 0.5.1
Summary: Small CLI for managing virtual python environments
Home-page: https://github.com/AckslD/manven
Author: Axel Dahlberg
Author-email: axel.dahlberg12@gmail.com
Classifier: Programming Language :: Python :: 3.6
Classifier: Programming Language :: Python :: 3.7
Classifier: Programming Language :: Python :: 3.8
Classifier: License :: OSI Approved :: MIT License
Classifier: Operating System :: Unix
Classifier: Operating System :: MacOS
Requires-Python: >=3.6
Requires-Dist: virtualenv (<21.0.0,>=16.0.0)
Requires-Dist: click (<9.0,>=7.0)
